fmuser/__init__.py
fmuser/fmuser.py
fmuser/modify_user.py
pyFmuser-1.2.dist-info/DESCRIPTION.rst
pyFmuser-1.2.dist-info/METADATA
pyFmuser-1.2.dist-info/RECORD
pyFmuser-1.2.dist-info/WHEEL
pyFmuser-1.2.dist-info/metadata.json
pyFmuser-1.2.dist-info/top_level.txt
tests/__init__.py
tests/fmuser_test.py
tests/test.py
