Metadata-Version: 2.0
Name: pyFmuser
Version: 1.2
Summary: A pure Python library designed to modify FREESWITCH's register user information in batch mode
Home-page: https://github.com/sudaning/Fmuser
Author: Daning Su
Author-email: sudaning@sina.com
License: LICENSE
Platform: linux
Classifier: Development Status :: 5 - Production/Stable
Classifier: Intended Audience :: Science/Research
Classifier: Natural Language :: Chinese (Simplified)
Classifier: Topic :: Text Processing
Classifier: Operating System :: POSIX :: Linux
Classifier: License :: OSI Approved :: MIT License
Classifier: Programming Language :: Python :: 2
Classifier: Programming Language :: Python :: 2.7
